kima/py.typed
kima/SPLEAFmodel.h
kima/GP.cpython-39-x86_64-linux-gnu.so
kima/GAIAmodel.h
kima/RVFWHMRHKmodel.cpython-39-x86_64-linux-gnu.so
kima/RVFWHMmodel.h
kima/RVmodel.cpp
kima/ETVmodel.h
kima/GP.h
kima/GP.cpp
kima/GAIAmodel.pyi
kima/ConditionalPrior.cpython-39-x86_64-linux-gnu.so
kima/Data.cpython-39-x86_64-linux-gnu.so
kima/distributions.cpp
kima/default_priors.cpp
kima/Data.cpp
kima/bessel-library.hpp
kima/kmath.cpp
kima/TRANSITmodel.cpp
kima/ETVmodel.cpp
kima/distributions.cpython-39-x86_64-linux-gnu.so
kima/kepler.pyi
kima/SPLEAFmodel.cpython-39-x86_64-linux-gnu.so
kima/run.cpp
kima/RVFWHMRHKmodel.cpp
kima/GPmodel.pyi
kima/BINARIESmodel.pyi
kima/transits.h
kima/OutlierRVmodel.h
kima/BINARIESmodel.cpp
kima/bessel-library.cpp
kima/Data.pyi
kima/Sampler.pyi
kima/RVGAIAmodel.pyi
kima/BINARIESmodel.h
kima/OutlierRVmodel.cpython-39-x86_64-linux-gnu.so
kima/SPLEAFmodel.cpp
kima/AMDstability.cpp
kima/default_priors.cpython-39-x86_64-linux-gnu.so
kima/RVGAIAmodel.cpython-39-x86_64-linux-gnu.so
kima/ETVmodel.cpython-39-x86_64-linux-gnu.so
kima/__init__.py
kima/RVGAIAmodel.h
kima/transits.cpp
kima/RVFWHMRHKmodel.pyi
kima/GPmodel.cpp
kima/AMDstability.h
kima/postkepler.h
kima/default_priors.h
kima/RVmodel.h
kima/SPLEAFmodel.pyi
kima/nb_shared.h
kima/kmath.h
kima/RVmodel.pyi
kima/TRANSITmodel.h
kima/ETVmodel.pyi
kima/OutlierRVmodel.cpp
kima/RVFWHMmodel.cpp
kima/RVFWHMmodel.pyi
kima/transits.cpython-39-x86_64-linux-gnu.so
kima/RVFWHMmodel.cpython-39-x86_64-linux-gnu.so
kima/kepler.h
kima/TRANSITmodel.pyi
kima/ConditionalPrior.cpp
kima/Sampler.cpython-39-x86_64-linux-gnu.so
kima/ConditionalPrior.h
kima/TRANSITmodel.cpython-39-x86_64-linux-gnu.so
kima/kepler.cpython-39-x86_64-linux-gnu.so
kima/GAIAmodel.cpp
kima/OutlierRVmodel.pyi
kima/RVFWHMRHKmodel.h
kima/utils.h
kima/Data.h
kima/distributions.pyi
kima/kmath.cpython-39-x86_64-linux-gnu.so
kima/AMDstability.cpython-39-x86_64-linux-gnu.so
kima-6.2.4.dist-info/WHEEL
kima-6.2.4.dist-info/METADATA
kima-6.2.4.dist-info/entry_points.txt
kima-6.2.4.dist-info/RECORD
kima-6.2.4.dist-info/licenses/LICENSE
