Metadata-Version: 2.1
Name: kima
Version: 6.2.4
Summary: A data analysis framework for exoplanet detection
Author-Email: "João Faria" <joao.faria@unige.ch>
License: MIT License
Classifier: Programming Language :: Python
Classifier: License :: OSI Approved :: MIT License
Project-URL: Homepage, http://www.kima.science
Project-URL: Documentation, http://www.kima.science/docs/
Project-URL: Repository, https://github.com/kima-org/kima
Project-URL: Issues, https://github.com/kima-org/kima
Requires-Python: >=3.9
Requires-Dist: typing_extensions
Requires-Dist: numpy
Requires-Dist: scipy
Requires-Dist: matplotlib
Requires-Dist: corner
Requires-Dist: loguniform
Requires-Dist: kumaraswamy
Requires-Dist: urepr
Requires-Dist: astropy
Requires-Dist: jaxlib
Requires-Dist: jax
Requires-Dist: rebound
Requires-Dist: psutil
Requires-Dist: tinygp
Provides-Extra: dev
Requires-Dist: nanobind; extra == "dev"
Requires-Dist: scikit-build-core[pyproject]; extra == "dev"
Requires-Dist: mkdocs; extra == "dev"
Requires-Dist: mkdocstrings[python]; extra == "dev"
Requires-Dist: mkdocs-autorefs; extra == "dev"
Requires-Dist: mkdocs-material; extra == "dev"
Requires-Dist: mkdocs-jupyter; extra == "dev"
Requires-Dist: mkdocs-git-revision-date-localized-plugin; extra == "dev"
